{
  "pipeline_version": "2.0.0",
  "run_timestamp": "2026-05-27T21:14:40.393255+00:00",
  "input_file": "/Users/priyansh/Desktop/Code/Scrapegraph-ai/data/ditto_raw_sitemap_dataset.jsonl",
  "output_dir": "/Users/priyansh/Desktop/Code/priyansh-insurance/data/rag",
  "input_records": 8832,
  "output_summary": {
    "cleaned_rag_chunks": 19008,
    "faq_records": 81,
    "claims_process_records": 6,
    "review_records": 141,
    "comparison_records": 7305,
    "insurer_profiles": 22,
    "total_output_records": 26563
  },
  "processing_stats": {
    "skipped_empty_after_clean": 3,
    "claims_sections": 6,
    "claims_pages": 14,
    "generic_chunks": 1410,
    "reviews": 141,
    "review_pages": 19,
    "comparisons": 7305,
    "faqs": 81
  },
  "content_type_dist": {
    "comparison": 13423,
    "policy_feature": 5515,
    "claims_process": 46,
    "review": 23,
    "customer_support": 1
  },
  "insurer_dist": {
    "unknown": 11541,
    "Care Health": 5428,
    "SBI Health": 203,
    "Star Health": 198,
    "HDFC Ergo": 185,
    "Niva Bupa": 185,
    "Aditya Birla Health": 168,
    "HDFC Life": 122,
    "ICICI Lombard": 96,
    "Tata AIA Life": 92,
    "Manipal Cigna": 89,
    "Max Life": 79,
    "Tata AIG": 72,
    "Bajaj Allianz Life": 64,
    "Reliance Health": 57,
    "Bajaj Allianz General": 55,
    "New India Assurance": 53,
    "ICICI Prudential Life": 43,
    "Acko Health": 37,
    "National Insurance": 35,
    "Oriental Insurance": 33,
    "Digit Insurance": 30,
    "Royal Sundaram": 29,
    "United India Insurance": 29,
    "Aditya Birla Sun Life": 19,
    "Universal Sompo": 16,
    "Kotak Life": 15,
    "Zuno Health": 13,
    "Navi Health": 12,
    "IFFCO Tokio": 10
  },
  "insurance_type_dist": {
    "health": 16316,
    "term": 2420,
    "general": 272
  },
  "category_dist": {
    "plan_comparison": 13423,
    "article": 4235,
    "insurer_subpage": 719,
    "insurer_page": 247,
    "insurer_overview": 199,
    "general": 79,
    "claims": 44,
    "health_general": 36,
    "insurer_reviews": 23,
    "claims_page": 2,
    "support_page": 1
  },
  "top_tags": {
    "claim": 15941,
    "health_insurance": 14717,
    "maternity": 13315,
    "ayush": 12950,
    "domiciliary": 12894,
    "sub_limit": 9810,
    "room_rent": 9106,
    "co_payment": 8890,
    "no_claim_bonus": 8401,
    "restoration": 8255,
    "network_hospital": 8064,
    "opd": 5621,
    "care_health": 5428,
    "premium": 4640,
    "chronic_disease": 4319,
    "waiting_period": 3404,
    "senior_citizen": 3180,
    "family_floater": 2676,
    "term_insurance": 2472,
    "diabetes": 1291,
    "critical_illness": 1200,
    "cashless": 990,
    "exclusion": 965,
    "top_up": 748,
    "deductible": 747,
    "reimbursement": 635,
    "hiv": 302,
    "sbi_health": 203,
    "star_health": 198,
    "hdfc_ergo": 185,
    "niva_bupa": 185,
    "aditya_birla_health": 168,
    "portability": 142,
    "hdfc_life": 122,
    "covid": 109,
    "icici_lombard": 96,
    "tata_aia_life": 92,
    "manipal_cigna": 89,
    "ombudsman": 88,
    "max_life": 79,
    "tata_aig": 72,
    "bajaj_allianz_life": 64,
    "reliance_health": 57,
    "bajaj_allianz_general": 55,
    "new_india_assurance": 53,
    "icici_prudential_life": 43,
    "acko_health": 37,
    "national_insurance": 35,
    "oriental_insurance": 33,
    "digit_insurance": 30
  },
  "review_sentiment_dist": {
    "positive": 74,
    "neutral": 53,
    "negative": 14
  }
}